{
  "Farming, Forestry, Animal Husbandry, Fishery and Water Conservancy      ": "1A4C",
  "Coal Mining and Dressing                                 ": "1A1C",
  "Petroleum and Natural Gas Extraction                     ": "1B2",
  "Ferrous Metals Mining and Dressing                       ": "1A2I",
  "Nonferrous Metals Mining and Dressing                    ": "1A2I",
  "Nonmetal Minerals Mining and Dressing                    ": "1A2I",
  "Other Minerals Mining and Dressing                       ": "1A2I",
  "Logging and Transport of Wood and Bamboo                 ": "1A2J",
  "Food Processing                                          ": "1A2E",
  "Food Production                                          ": "1A2E",
  "Beverage Production": "1A2E",
  "Tobacco Processing                                       ": "1A2E",
  "Textile Industry                                         ": "1A2L",
  "Garments and Other Fiber Products                        ": "1A2L",
  "Leather, Furs, Down and Related Products                 ": "1A2L",
  "Timber Processing, Bamboo, Cane, Palm Fiber & Straw Products": "1A2J",
  "Furniture Manufacturing                                  ": "1A2J",
  "Papermaking and Paper Products                           ": "1A2D",
  "Printing and Record Medium Reproduction                  ": "1A2D",
  "Cultural, Educational and Sports Articles                ": "1A2D",
  "Petroleum Processing and Coking                          ": "1A1B",
  "Raw Chemical Materials and Chemical Products             ": "1A2C",
  "Medical and Pharmaceutical Products                      ": "1A2C",
  "Chemical Fiber                                           ": "1A2C",
  "Rubber Products                                          ": "1A2C",
  "Plastic Products                                         ": "1A2C",
  "Nonmetal Mineral Products                                ": "1A2F",
  "Smelting and Pressing of Ferrous Metals                  ": "1A2A",
  "Smelting and Pressing of Nonferrous Metals               ": "1A2B",
  "Metal Products                                           ": "1A2A",
  "Ordinary Machinery                                       ": "1A2H",
  "Equipment for Special Purposes                           ": "1A2H",
  "Transportation Equipment                                 ": "1A2G",
  "Electric Equipment and Machinery                         ": "1A2H",
  "Electronic and Telecommunications Equipment              ": "1A2H",
  "Instruments, Meters, Cultural and Office Machinery         ": "1A2H",
  "Other Manufacturing Industry                             ": "1A2M",
  "Scrap and waste": "1A2M",
  "Production and Supply of Electric Power, Steam and Hot Water   ": "1A1A1",
  "Production and Supply of Gas                             ": "1B2B",
  "Production and Supply of Tap Water                       ": "1A4A",
  "Construction                                             ": "1A2K",
  "Transportation, Storage, Post and Telecommunication Services    ": "1A3",
  "Wholesale, Retail Trade and Catering Services            ": "1A4A",
  "Others                                                   ": "1A5",
  "Urban": "1A4B",
  "Rural": "1A4B"
}